games_box/__init__.py
games_box/animals.py
games_box/colours.py
games_box/dice.py
games_box-0.0.1.dist-info/METADATA
games_box-0.0.1.dist-info/WHEEL
games_box-0.0.1.dist-info/top_level.txt
games_box-0.0.1.dist-info/RECORD
