Metadata-Version: 2.1
Name: games-box
Version: 0.0.1
Summary: Various games tools
Home-page: UNKNOWN
Author: Adam Chester
Author-email: achester.dev@gmail.com
License: UNKNOWN
Platform: UNKNOWN
Requires-Python: >=3.7
Requires-Dist: click8 (~=8.0.1)
